{"created_at":"Sun Apr 05 10:47:09 +0000 2020","id":1246751221614088193,"id_str":"1246751221614088193","text":"RT @binsungcult: i dont care how big your fandom is or how impossible it is that your idol will see your posts, Censor Your Nsfw Content. t\u2026","source":"\u003ca href=\"http:\/\/twitter.com\/download\/android\" rel=\"nofollow\"\u003eTwitter for Android\u003c\/a\u003e","truncated":false,"in_reply_to_status_id":null,"in_reply_to_status_id_str":null,"in_reply_to_user_id":null,"in_reply_to_user_id_str":null,"in_reply_to_screen_name":null,"user":{"id":1105450220857507840,"id_str":"1105450220857507840","name":"\ud835\udc70'\ud835\udc8e \ud835\udc83\ud835\udc82\ud835\udc83\ud835\udc8a\ud835\udc86","screen_name":"nsfwlixie","location":null,"url":null,"description":"Cries.","translator_type":"none","protected":false,"verified":false,"followers_count":21,"friends_count":147,"listed_count":1,"favourites_count":9420,"statuses_count":2813,"created_at":"Tue Mar 12 12:47:25 +0000 2019","utc_offset":null,"time_zone":null,"geo_enabled":false,"lang":null,"contributors_enabled":false,"is_translator":false,"profile_background_color":"F5F8FA","profile_background_image_url":"","profile_background_image_url_https":"","profile_background_tile":false,"profile_link_color":"1DA1F2","profile_sidebar_border_color":"C0DEED","profile_sidebar_fill_color":"DDEEF6","profile_text_color":"333333","profile_use_background_image":true,"profile_image_url":"http:\/\/pbs.twimg.com\/profile_images\/1239295209474871301\/7O4a0nvW_normal.jpg","profile_image_url_https":"https:\/\/pbs.twimg.com\/profile_images\/1239295209474871301\/7O4a0nvW_normal.jpg","profile_banner_url":"https:\/\/pbs.twimg.com\/profile_banners\/1105450220857507840\/1584305975","default_profile":true,"default_profile_image":false,"following":null,"follow_request_sent":null,"notifications":null},"geo":null,"coordinates":null,"place":null,"contributors":null,"retweeted_status":{"created_at":"Sun Apr 05 06:24:20 +0000 2020","id":1246685082871570433,"id_str":"1246685082871570433","text":"i dont care how big your fandom is or how impossible it is that your idol will see your posts, Censor Your Nsfw Con\u2026 https:\/\/t.co\/XgyvbtWR65","source":"\u003ca href=\"http:\/\/twitter.com\/download\/android\" rel=\"nofollow\"\u003eTwitter for Android\u003c\/a\u003e","truncated":true,"in_reply_to_status_id":null,"in_reply_to_status_id_str":null,"in_reply_to_user_id":null,"in_reply_to_user_id_str":null,"in_reply_to_screen_name":null,"user":{"id":1158940848081559552,"id_str":"1158940848081559552","name":"\u22f0 \ud835\udc0b\ud835\udc18, \ud835\udc01\u00a1\ud835\udc0d\ud835\udc12\ud835\udc14\ud835\udc0d\ud835\udc06 \ud835\udc02\ud835\udc14\ud835\udc0b\ud835\udc13 \ud835\udc0b\ud835\udc04\ud835\udc00\ud835\udc03\ud835\udc04\ud835\udc11\u22f1","screen_name":"binsungcult","location":"\ud835\udc0d\ud835\udc12\ud835\udc05\ud835\udc16 || \ud835\udfcf\ud835\udfd4+ || \ud835\udfcf\ud835\udfd5","url":"https:\/\/curiouscat.me\/binsungcult","description":"\u2730 #\ud835\udc09\ud835\udc08\ud835\udc12\ud835\udc15\ud835\udc0d\ud835\udc06: \ucc3d\ube48 \ubaac\uc2a4\ud130 \ucf55\n                                                             \u2727 \ud835\udc0e\ud835\udc02\ud835\udc02\ud835\udc00\ud835\udc12\ud835\udc08\ud835\udc0e\ud835\udc0d\ud835\udc00\ud835\udc0b \ud835\udc15\ud835\udc08\ud835\udc0e\ud835\udc0b\ud835\udc04\ud835\udc0d\ud835\udc02\ud835\udc04 \ud835\udc13\ud835\udc16, \ud835\udc01\ud835\udc04 \ud835\udc00\ud835\udc16\ud835\udc00\ud835\udc11\ud835\udc04","translator_type":"none","protected":false,"verified":false,"followers_count":1722,"friends_count":229,"listed_count":35,"favourites_count":24897,"statuses_count":18030,"created_at":"Wed Aug 07 03:20:05 +0000 2019","utc_offset":null,"time_zone":null,"geo_enabled":false,"lang":null,"contributors_enabled":false,"is_translator":false,"profile_background_color":"F5F8FA","profile_background_image_url":"","profile_background_image_url_https":"","profile_background_tile":false,"profile_link_color":"1DA1F2","profile_sidebar_border_color":"C0DEED","profile_sidebar_fill_color":"DDEEF6","profile_text_color":"333333","profile_use_background_image":true,"profile_image_url":"http:\/\/pbs.twimg.com\/profile_images\/1246272397621309442\/HBgQ6eOs_normal.png","profile_image_url_https":"https:\/\/pbs.twimg.com\/profile_images\/1246272397621309442\/HBgQ6eOs_normal.png","profile_banner_url":"https:\/\/pbs.twimg.com\/profile_banners\/1158940848081559552\/1585837295","default_profile":true,"default_profile_image":false,"following":null,"follow_request_sent":null,"notifications":null},"geo":null,"coordinates":null,"place":null,"contributors":null,"is_quote_status":false,"extended_tweet":{"full_text":"i dont care how big your fandom is or how impossible it is that your idol will see your posts, Censor Your Nsfw Content. there are people in this world who can become heavily triggered by nsfw themes, and when they search their idols name? the last thing they want is to be+","display_text_range":[0,274],"entities":{"hashtags":[],"urls":[],"user_mentions":[],"symbols":[]}},"quote_count":2,"reply_count":1,"retweet_count":29,"favorite_count":77,"entities":{"hashtags":[],"urls":[{"url":"https:\/\/t.co\/XgyvbtWR65","expanded_url":"https:\/\/twitter.com\/i\/web\/status\/1246685082871570433","display_url":"twitter.com\/i\/web\/status\/1\u2026","indices":[117,140]}],"user_mentions":[],"symbols":[]},"favorited":false,"retweeted":false,"filter_level":"low","lang":"en"},"is_quote_status":false,"quote_count":0,"reply_count":0,"retweet_count":0,"favorite_count":0,"entities":{"hashtags":[],"urls":[],"user_mentions":[{"screen_name":"binsungcult","name":"\u22f0 \ud835\udc0b\ud835\udc18, \ud835\udc01\u00a1\ud835\udc0d\ud835\udc12\ud835\udc14\ud835\udc0d\ud835\udc06 \ud835\udc02\ud835\udc14\ud835\udc0b\ud835\udc13 \ud835\udc0b\ud835\udc04\ud835\udc00\ud835\udc03\ud835\udc04\ud835\udc11\u22f1","id":1158940848081559552,"id_str":"1158940848081559552","indices":[3,15]}],"symbols":[]},"favorited":false,"retweeted":false,"filter_level":"low","lang":"en","timestamp_ms":"1586083629407"}
